<!DOCTYPE ui:UiBinder SYSTEM "http://dl.google.com/gwt/DTD/xhtml.ent">
<ui:UiBinder xmlns:ui="urn:ui:com.google.gwt.uibinder"
	xmlns:g="urn:import:com.google.gwt.user.client.ui">
	<ui:style>
		.important {
			font-weight: bold;
		}
		.description{
	        color:#9152a0;
	        margin: 30px;
	   }
	</ui:style>
	<g:HTMLPanel>
	   <div class="{style.description}">
	    <h1>JOY</h1>
		It reserves time for the children to play alone and in group. 
    		    It encourages social games and good relationship between children to increase 
    		    the sense of family. The games should happen in an safe environment with the 
    		    surveillance of an appropriate number of adults which are encouraged to participate 
    		    and cheer them. The games should be adapted in order to make all children 
    		    participating independently of personal issues such diseases or handicaps.
		</div>
	</g:HTMLPanel>
</ui:UiBinder> 